Metadata-Version: 2.1
Name: sqlIite
Version: 0.4
Summary: Gaussian and Binomial distributions
